README.md
setup.py
lazyimport/__init__.py
noimport/__init__.py
presets/__init__.py
presets/core.py
wrappingpaper/__init__.py
wrappingpaper/concurrent.py
wrappingpaper/context.py
wrappingpaper/exceptions.py
wrappingpaper/importmechanics.py
wrappingpaper/iters.py
wrappingpaper/logs.py
wrappingpaper/misc.py
wrappingpaper/objects.py
wrappingpaper/props.py
wrappingpaper/schedule.py
wrappingpaper/signature.py
wrappingpaper/stack.py
wrappingpaper/text.py
wrappingpaper.egg-info/PKG-INFO
wrappingpaper.egg-info/SOURCES.txt
wrappingpaper.egg-info/dependency_links.txt
wrappingpaper.egg-info/top_level.txt