Metadata-Version: 2.1
Name: wrappingpaper
Version: 0.0.6
Summary: UNKNOWN
Home-page: https://github.com/beasteers/wrappingpaper
Author: Bea Steers
Author-email: bea.steers@gmail.com
License: MIT License
Platform: UNKNOWN
